djlotrek/__init__.py
djlotrek/aes.py
djlotrek/context_processors.py
djlotrek/decorators.py
djlotrek/mail_utils.py
djlotrek/request_utils.py
djlotrek/rosetta_utils.py
djlotrek/utils.py
djlotrek/widgets.py
djlotrek/middleware/__init__.py
djlotrek/middleware/cache.py
djlotrek/middleware/cache_admin.py
djlotrek/middleware/cache_header.py
djlotrek/middleware/cache_url.py
djlotrek/middleware/locale.py
djlotrek/templates/djlotrek/widgets/related_one_to_one_widget_wrapper.html
djlotrek/templatetags/__init__.py
djlotrek/templatetags/djlotrek_filters.py
djlotrek/templatetags/djlotrek_tags.py
tests/__init__.py
tests/test_aes.py
tests/test_contextprocessors.py
tests/test_mail_utils.py
tests/test_request_utils.py
tests/test_templatefilters.py
tests/test_templatetags.py
tests/test_utils.py
tests/urls.py
djlotrek-0.1.7.dist-info/LICENSE
djlotrek-0.1.7.dist-info/METADATA
djlotrek-0.1.7.dist-info/WHEEL
djlotrek-0.1.7.dist-info/top_level.txt
djlotrek-0.1.7.dist-info/RECORD
