Metadata-Version: 2.1
Name: djlotrek
Version: 0.1.7
Summary: Lotrek beloved Django utilities library
Home-page: https://github.com/lotrekagency/djlotrek
Author: Lotrèk
Author-email: dimmitutto@lotrek.it
License: MIT
Keywords: cms,django,api cms
Platform: UNKNOWN
Classifier: Environment :: Web Environment
Classifier: Framework :: Django
Classifier: Intended Audience :: Developers
Classifier: Programming Language :: Python
Classifier: Programming Language :: Python :: 3
Requires-Python: >=3.0.*
License-File: LICENSE
Requires-Dist: pycryptodome (>=3.9.8)
Requires-Dist: requests (>=2.18.4)
Requires-Dist: Django (>=1.8)
